loopwn/__init__.py
loopwn/looplibc.py
loopwn-0.1.0.dist-info/licenses/LICENSE
loopwn-0.1.0.dist-info/METADATA
loopwn-0.1.0.dist-info/WHEEL
loopwn-0.1.0.dist-info/top_level.txt
loopwn-0.1.0.dist-info/RECORD
