Metadata-Version: 2.4
Name: loopwn
Version: 0.1.0
Summary: A CTF pwn helper library for easy libc address calculation
Home-page: https://github.com/loophatch/loopwn
Author: loophatch
Author-email: loophatch@example.com
Classifier: Programming Language :: Python :: 3
Classifier: License :: OSI Approved :: MIT License
Classifier: Operating System :: OS Independent
Requires-Python: >=3.6
License-File: LICENSE
Requires-Dist: pwntools
Dynamic: author
Dynamic: author-email
Dynamic: classifier
Dynamic: description
Dynamic: description-content-type
Dynamic: home-page
Dynamic: license-file
Dynamic: requires-dist
Dynamic: requires-python
Dynamic: summary
